Workbook
Name ProgramStart: 'Start Here'!$B$4

Sheet Start Here
A1: BSA Onboarding Trackers
A2: Skills, knowledge, tool inventory and glossary for Hire A (Research) and Hire B (Standard Cost)
A4: Program start (Day 1) | B4: 46314
A5: Day 30 review | B5: 46344
A6: Day 60 review | B6: 46374
A7: Day 90 review | B7: 46402
A9: Proficiency scale
A10: 0 | B10: Not yet exposed
A11: 1 | B11: Aware: can explain the basics
A12: 2 | B12: Guided: does it with help
A13: 3 | B13: Independent: does it alone; work is reviewed
A14: 4 | B14: Owns/teaches: runs it, improves it, can train others
A16: How to use
A17: • | B17: Yellow cells are inputs. Everything else is reference data or formulas.
A18: • | B18: Skills tabs: the hire updates 'Current self-rating' every Friday. At each milestone review the trainer enters the agreed rating in 'Rating @Dxx'. Green = at or above target, amber = one below, red = two or more below.
A19: • | B19: Knowledge tabs: the hire updates Status, Date covered and Confidence as topics are taught. A Status cell turns red when its target week has passed and the topic is not yet Covered.
A20: • | B20: Tool Inventory: the hires fill this in during week 2 (split the tools between them). It becomes the team's first catalog of custom tools.
A21: • | B21: Dashboard: rolls up % of skills at target per milestone. Review it in the weekly 1:1.
A22: • | B22: Generic-only: replace [COMPANY: ...] placeholders on company systems, not in the source repo.

Sheet Dashboard
A1: Dashboard
A2: Formulas only. Ratings come from the Skills tabs; status from the Knowledge tabs.
A4: Skills at or above target (skills with target > 0)
A5: Hire | B5: Milestone | C5: Skills with target | D5: Rated | E5: At target | F5: % at target
A6: Hire A | B6: Day 30 | C6: =COUNTIF('Skills - Hire A'!$F$5:$F$79,">0") | D6: =COUNT('Skills - Hire A'!$G$5:$G$79) | E6: =SUMPRODUCT(('Skills - Hire A'!$G$5:$G$79<>"")*('Skills - Hire A'!$F$5:$F$79>0)*('Skills - Hire A'!$G$5:$G$79>='Skills - Hire A'!$F$5:$F$79)) | F6: =IF(D6=0,"",E6/C6)
A7: Hire A | B7: Day 60 | C7: =COUNTIF('Skills - Hire A'!$H$5:$H$79,">0") | D7: =COUNT('Skills - Hire A'!$I$5:$I$79) | E7: =SUMPRODUCT(('Skills - Hire A'!$I$5:$I$79<>"")*('Skills - Hire A'!$H$5:$H$79>0)*('Skills - Hire A'!$I$5:$I$79>='Skills - Hire A'!$H$5:$H$79)) | F7: =IF(D7=0,"",E7/C7)
A8: Hire A | B8: Day 90 | C8: =COUNTIF('Skills - Hire A'!$J$5:$J$79,">0") | D8: =COUNT('Skills - Hire A'!$K$5:$K$79) | E8: =SUMPRODUCT(('Skills - Hire A'!$K$5:$K$79<>"")*('Skills - Hire A'!$J$5:$J$79>0)*('Skills - Hire A'!$K$5:$K$79>='Skills - Hire A'!$J$5:$J$79)) | F8: =IF(D8=0,"",E8/C8)
A9: Hire B | B9: Day 30 | C9: =COUNTIF('Skills - Hire B'!$F$5:$F$79,">0") | D9: =COUNT('Skills - Hire B'!$G$5:$G$79) | E9: =SUMPRODUCT(('Skills - Hire B'!$G$5:$G$79<>"")*('Skills - Hire B'!$F$5:$F$79>0)*('Skills - Hire B'!$G$5:$G$79>='Skills - Hire B'!$F$5:$F$79)) | F9: =IF(D9=0,"",E9/C9)
A10: Hire B | B10: Day 60 | C10: =COUNTIF('Skills - Hire B'!$H$5:$H$79,">0") | D10: =COUNT('Skills - Hire B'!$I$5:$I$79) | E10: =SUMPRODUCT(('Skills - Hire B'!$I$5:$I$79<>"")*('Skills - Hire B'!$H$5:$H$79>0)*('Skills - Hire B'!$I$5:$I$79>='Skills - Hire B'!$H$5:$H$79)) | F10: =IF(D10=0,"",E10/C10)
A11: Hire B | B11: Day 90 | C11: =COUNTIF('Skills - Hire B'!$J$5:$J$79,">0") | D11: =COUNT('Skills - Hire B'!$K$5:$K$79) | E11: =SUMPRODUCT(('Skills - Hire B'!$K$5:$K$79<>"")*('Skills - Hire B'!$J$5:$J$79>0)*('Skills - Hire B'!$K$5:$K$79>='Skills - Hire B'!$J$5:$J$79)) | F11: =IF(D11=0,"",E11/C11)
A13: Average current self-rating vs Day 90 target, by module
A14: Module | B14: Hire A self-rating | C14: Hire A D90 target | D14: Hire B self-rating | E14: Hire B D90 target
A15: M0 | B15: =IFERROR(AVERAGEIFS('Skills - Hire A'!$L$5:$L$79,'Skills - Hire A'!$B$5:$B$79,A15),"") | C15: =IFERROR(AVERAGEIFS('Skills - Hire A'!$J$5:$J$79,'Skills - Hire A'!$B$5:$B$79,A15),"") | D15: =IFERROR(AVERAGEIFS('Skills - Hire B'!$L$5:$L$79,'Skills - Hire B'!$B$5:$B$79,A15),"") | E15: =IFERROR(AVERAGEIFS('Skills - Hire B'!$J$5:$J$79,'Skills - Hire B'!$B$5:$B$79,A15),"")
A16: M1 | B16: =IFERROR(AVERAGEIFS('Skills - Hire A'!$L$5:$L$79,'Skills - Hire A'!$B$5:$B$79,A16),"") | C16: =IFERROR(AVERAGEIFS('Skills - Hire A'!$J$5:$J$79,'Skills - Hire A'!$B$5:$B$79,A16),"") | D16: =IFERROR(AVERAGEIFS('Skills - Hire B'!$L$5:$L$79,'Skills - Hire B'!$B$5:$B$79,A16),"") | E16: =IFERROR(AVERAGEIFS('Skills - Hire B'!$J$5:$J$79,'Skills - Hire B'!$B$5:$B$79,A16),"")
A17: M2 | B17: =IFERROR(AVERAGEIFS('Skills - Hire A'!$L$5:$L$79,'Skills - Hire A'!$B$5:$B$79,A17),"") | C17: =IFERROR(AVERAGEIFS('Skills - Hire A'!$J$5:$J$79,'Skills - Hire A'!$B$5:$B$79,A17),"") | D17: =IFERROR(AVERAGEIFS('Skills - Hire B'!$L$5:$L$79,'Skills - Hire B'!$B$5:$B$79,A17),"") | E17: =IFERROR(AVERAGEIFS('Skills - Hire B'!$J$5:$J$79,'Skills - Hire B'!$B$5:$B$79,A17),"")
A18: M3 | B18: =IFERROR(AVERAGEIFS('Skills - Hire A'!$L$5:$L$79,'Skills - Hire A'!$B$5:$B$79,A18),"") | C18: =IFERROR(AVERAGEIFS('Skills - Hire A'!$J$5:$J$79,'Skills - Hire A'!$B$5:$B$79,A18),"") | D18: =IFERROR(AVERAGEIFS('Skills - Hire B'!$L$5:$L$79,'Skills - Hire B'!$B$5:$B$79,A18),"") | E18: =IFERROR(AVERAGEIFS('Skills - Hire B'!$J$5:$J$79,'Skills - Hire B'!$B$5:$B$79,A18),"")
A19: M4 | B19: =IFERROR(AVERAGEIFS('Skills - Hire A'!$L$5:$L$79,'Skills - Hire A'!$B$5:$B$79,A19),"") | C19: =IFERROR(AVERAGEIFS('Skills - Hire A'!$J$5:$J$79,'Skills - Hire A'!$B$5:$B$79,A19),"") | D19: =IFERROR(AVERAGEIFS('Skills - Hire B'!$L$5:$L$79,'Skills - Hire B'!$B$5:$B$79,A19),"") | E19: =IFERROR(AVERAGEIFS('Skills - Hire B'!$J$5:$J$79,'Skills - Hire B'!$B$5:$B$79,A19),"")
A20: M5R | B20: =IFERROR(AVERAGEIFS('Skills - Hire A'!$L$5:$L$79,'Skills - Hire A'!$B$5:$B$79,A20),"") | C20: =IFERROR(AVERAGEIFS('Skills - Hire A'!$J$5:$J$79,'Skills - Hire A'!$B$5:$B$79,A20),"") | D20: =IFERROR(AVERAGEIFS('Skills - Hire B'!$L$5:$L$79,'Skills - Hire B'!$B$5:$B$79,A20),"") | E20: =IFERROR(AVERAGEIFS('Skills - Hire B'!$J$5:$J$79,'Skills - Hire B'!$B$5:$B$79,A20),"")
A21: M5C | B21: =IFERROR(AVERAGEIFS('Skills - Hire A'!$L$5:$L$79,'Skills - Hire A'!$B$5:$B$79,A21),"") | C21: =IFERROR(AVERAGEIFS('Skills - Hire A'!$J$5:$J$79,'Skills - Hire A'!$B$5:$B$79,A21),"") | D21: =IFERROR(AVERAGEIFS('Skills - Hire B'!$L$5:$L$79,'Skills - Hire B'!$B$5:$B$79,A21),"") | E21: =IFERROR(AVERAGEIFS('Skills - Hire B'!$J$5:$J$79,'Skills - Hire B'!$B$5:$B$79,A21),"")
A22: M6 | B22: =IFERROR(AVERAGEIFS('Skills - Hire A'!$L$5:$L$79,'Skills - Hire A'!$B$5:$B$79,A22),"") | C22: =IFERROR(AVERAGEIFS('Skills - Hire A'!$J$5:$J$79,'Skills - Hire A'!$B$5:$B$79,A22),"") | D22: =IFERROR(AVERAGEIFS('Skills - Hire B'!$L$5:$L$79,'Skills - Hire B'!$B$5:$B$79,A22),"") | E22: =IFERROR(AVERAGEIFS('Skills - Hire B'!$J$5:$J$79,'Skills - Hire B'!$B$5:$B$79,A22),"")
A23: M7 | B23: =IFERROR(AVERAGEIFS('Skills - Hire A'!$L$5:$L$79,'Skills - Hire A'!$B$5:$B$79,A23),"") | C23: =IFERROR(AVERAGEIFS('Skills - Hire A'!$J$5:$J$79,'Skills - Hire A'!$B$5:$B$79,A23),"") | D23: =IFERROR(AVERAGEIFS('Skills - Hire B'!$L$5:$L$79,'Skills - Hire B'!$B$5:$B$79,A23),"") | E23: =IFERROR(AVERAGEIFS('Skills - Hire B'!$J$5:$J$79,'Skills - Hire B'!$B$5:$B$79,A23),"")
A24: M8 | B24: =IFERROR(AVERAGEIFS('Skills - Hire A'!$L$5:$L$79,'Skills - Hire A'!$B$5:$B$79,A24),"") | C24: =IFERROR(AVERAGEIFS('Skills - Hire A'!$J$5:$J$79,'Skills - Hire A'!$B$5:$B$79,A24),"") | D24: =IFERROR(AVERAGEIFS('Skills - Hire B'!$L$5:$L$79,'Skills - Hire B'!$B$5:$B$79,A24),"") | E24: =IFERROR(AVERAGEIFS('Skills - Hire B'!$J$5:$J$79,'Skills - Hire B'!$B$5:$B$79,A24),"")
A25: M9 | B25: =IFERROR(AVERAGEIFS('Skills - Hire A'!$L$5:$L$79,'Skills - Hire A'!$B$5:$B$79,A25),"") | C25: =IFERROR(AVERAGEIFS('Skills - Hire A'!$J$5:$J$79,'Skills - Hire A'!$B$5:$B$79,A25),"") | D25: =IFERROR(AVERAGEIFS('Skills - Hire B'!$L$5:$L$79,'Skills - Hire B'!$B$5:$B$79,A25),"") | E25: =IFERROR(AVERAGEIFS('Skills - Hire B'!$J$5:$J$79,'Skills - Hire B'!$B$5:$B$79,A25),"")
A26: M10 | B26: =IFERROR(AVERAGEIFS('Skills - Hire A'!$L$5:$L$79,'Skills - Hire A'!$B$5:$B$79,A26),"") | C26: =IFERROR(AVERAGEIFS('Skills - Hire A'!$J$5:$J$79,'Skills - Hire A'!$B$5:$B$79,A26),"") | D26: =IFERROR(AVERAGEIFS('Skills - Hire B'!$L$5:$L$79,'Skills - Hire B'!$B$5:$B$79,A26),"") | E26: =IFERROR(AVERAGEIFS('Skills - Hire B'!$J$5:$J$79,'Skills - Hire B'!$B$5:$B$79,A26),"")
... A29: M13 | B29: =IFERROR(AVERAGEIFS('Skills - Hire A'!$L$5:$L$79,'Skills - Hire A'!$B$5:$B$79,A29),"") | C29: =IFERROR(AVERAGEIFS('Skills - Hire A'!$J$5:$J$79,'Skills - Hire A'!$B$5:$B$79,A29),"") | D29: =IFERROR(AVERAGEIFS('Skills - Hire B'!$L$5:$L$79,'Skills - Hire B'!$B$5:$B$79,A29),"") | E29: =IFERROR(AVERAGEIFS('Skills - Hire B'!$J$5:$J$79,'Skills - Hire B'!$B$5:$B$79,A29),"")
A31: Knowledge topics by status
A32: Hire | B32: Not started | C32: In progress | D32: Covered | E32: Teach-back done | F32: Overdue
A33: Hire A | B33: =COUNTIF('Knowledge - Hire A'!$J$5:$J$143,"Not started") | C33: =COUNTIF('Knowledge - Hire A'!$J$5:$J$143,"In progress") | D33: =COUNTIF('Knowledge - Hire A'!$J$5:$J$143,"Covered") | E33: =COUNTIF('Knowledge - Hire A'!$J$5:$J$143,"Teach-back done") | F33: =SUMPRODUCT((TODAY()>'Knowledge - Hire A'!$I$5:$I$143+4)*('Knowledge - Hire A'!$J$5:$J$143<>"Covered")*('Knowledge - Hire A'!$J$5:$J$143<>"Teach-back done"))
A34: Hire B | B34: =COUNTIF('Knowledge - Hire B'!$J$5:$J$143,"Not started") | C34: =COUNTIF('Knowledge - Hire B'!$J$5:$J$143,"In progress") | D34: =COUNTIF('Knowledge - Hire B'!$J$5:$J$143,"Covered") | E34: =COUNTIF('Knowledge - Hire B'!$J$5:$J$143,"Teach-back done") | F34: =SUMPRODUCT((TODAY()>'Knowledge - Hire B'!$I$5:$I$143+4)*('Knowledge - Hire B'!$J$5:$J$143<>"Covered")*('Knowledge - Hire B'!$J$5:$J$143<>"Teach-back done"))

Sheet Skills - Hire A
A1: Skills tracker: Hire A (Research track)
A2: Scale 0-4 (see Start Here). Targets come from the 30/60/90 plan.
A4: Skill ID | B4: Module | C4: Category | D4: Skill | E4: What good looks like (level 3) | F4: Target D30 | G4: Rating @D30 | H4: Target D60 | I4: Rating @D60 | J4: Target D90 | K4: Rating @D90 | L4: Current self-rating | M4: Evidence / notes
A5: S-M0-01 | B5: M0 | C5: Professional | D5: Plan and protect the 40-hour week | E5: Each Friday drafts next week's plan (three outcomes, fixed commitments, booked reviews, 15% unplanned), agrees the top 3 in the 1:1, confirms it at the Monday confirm, blocks self-study, Anki and documentation time as in docs/05-time-management.md, and flags a slip to the Manager at the midpoint check, not at the deadline. | F5: 2 | H5: 3 | J5: 3
A6: S-M0-02 | B6: M0 | C6: Professional | D6: Ask good questions | E6: Searches the primers, glossary and OneNote for 15 minutes first, logs each question with context, what was checked and a proposed answer, and turns reusable answers into a card, glossary entry or SOP line within 2 working days. | F6: 2 | H6: 3 | J6: 3
A7: S-M0-03 | B7: M0 | C7: Work tracking | D7: Keep own work visible in Jira | E7: Every piece of own work has a Jira item with a clear title, acceptance criteria and a status updated at least twice a week, and active work stays within the agreed work-in-progress limit. | F7: 3 | H7: 3 | J7: 3
A8: S-M0-04 | B8: M0 | C8: Communication | D8: Write clear status updates for stakeholders | E8: Writes Friday self-reports and stakeholder updates that lead with the answer and state impact, dates, risks and asks, and they go out without the Manager rewriting them. | F8: 2 | H8: 2 | J8: 3
A9: S-M0-05 | B9: M0 | C9: Documentation | D9: Capture knowledge as reviewed docs and Anki cards | E9: Turns sessions, shadowing and answered questions into OneNote pages, SOP lines and company-specific Anki cards with a Draft, Reviewed or Published status, and the cards pass the milestone spot check with zero factual errors. | F9: 2 | H9: 3 | J9: 3
A10: S-M0-06 | B10: M0 | C10: Communication | D10: Deliver a teach-back | E10: Explains a topic in 15 minutes using docs/templates/knowledge/teach-back.md, answers follow-up questions without notes, and says what they do not know instead of guessing. | F10: 2 | H10: 3 | J10: 3
A11: S-M0-07 | B11: M0 | C11: Business orientation | D11: Explain the business and its stakeholders | E11: Without notes, explains what we import, from where and into which countries, and keeps a 1-page stakeholder map showing what each group needs from the team and how tariff and cost news reaches them. | F11: 2 | H11: 3 | J11: 3
A12: S-M1-01 | B12: M1 | C12: Customs fundamentals | D12: Explain the life of a US import entry and who does what | E12: Without notes, walks through release, entry summary (CBP Form 7501), duty payment, liquidation and the protest window, and states what the importer of record, the licensed broker and CBP each own. | F12: 2 | H12: 3 | J12: 3
A13: S-M1-02 | B13: M1 | C13: Customs fundamentals | D13: Explain the Canada and Mexico import processes | E13: Explains the CBSA flow (release, CARM, Commercial Accounting Declaration, BN/RM account) and the Mexico flow (agente aduanal, pedimento, padrón de importadores, IVA), and names the data our team provides to each broker. | F13: 2 | H13: 2 | J13: 3
A14: S-M1-03 | B14: M1 | C14: Classification | D14: Classify an item using the GRIs | E14: Classifies a new item to 6-digit HS with written GRI reasoning backed by section and chapter notes, Explanatory Notes and CROSS rulings, finds the national line in the HTSUS, the Canada Customs Tariff and TIGIE, and flags doubtful cases for review. | F14: 2 | H14: 3 | J14: 3
A15: S-M1-04 | B15: M1 | C15: Customs fundamentals | D15: Calculate duties and fees for an entry line | E15: For an entry line, identifies the value basis, the rate column (general, USMCA or other preference, Chapter 99 additional duties) and fees such as MPF and HMF, and recomputes the duty to the cent or explains the difference. | F15: 2 | H15: 3 | J15: 3
A16: S-M1-05 | B16: M1 | C16: Origin & programs | D16: Apply USMCA rules of origin and certification | E16: Tests an item against its product-specific rule (tariff shift, RVC, de minimis) using its bill of materials, checks a certification for the nine minimum data elements, and states the importer's obligations if the claim fails. | F16: 2 | H16: 3 | J16: 3
... A79: S-M13-03 | B79: M13 | C79: SDLC | D79: Classify a change and plan its rollback | E79: Classifies each change as standard, normal or emergency, tells incidents, problems and changes apart, and writes a rollback plan with a verified backup, data clean-up steps and who is told, before any release. | F79: 0 | H79: 2 | J79: 3

Sheet Skills - Hire B
A1: Skills tracker: Hire B (Standard Cost track)
A2: Scale 0-4 (see Start Here). Targets come from the 30/60/90 plan.
A4: Skill ID | B4: Module | C4: Category | D4: Skill | E4: What good looks like (level 3) | F4: Target D30 | G4: Rating @D30 | H4: Target D60 | I4: Rating @D60 | J4: Target D90 | K4: Rating @D90 | L4: Current self-rating | M4: Evidence / notes
A5: S-M0-01 | B5: M0 | C5: Professional | D5: Plan and protect the 40-hour week | E5: Each Friday drafts next week's plan (three outcomes, fixed commitments, booked reviews, 15% unplanned), agrees the top 3 in the 1:1, confirms it at the Monday confirm, blocks self-study, Anki and documentation time as in docs/05-time-management.md, and flags a slip to the Manager at the midpoint check, not at the deadline. | F5: 2 | H5: 3 | J5: 3
A6: S-M0-02 | B6: M0 | C6: Professional | D6: Ask good questions | E6: Searches the primers, glossary and OneNote for 15 minutes first, logs each question with context, what was checked and a proposed answer, and turns reusable answers into a card, glossary entry or SOP line within 2 working days. | F6: 2 | H6: 3 | J6: 3
A7: S-M0-03 | B7: M0 | C7: Work tracking | D7: Keep own work visible in Jira | E7: Every piece of own work has a Jira item with a clear title, acceptance criteria and a status updated at least twice a week, and active work stays within the agreed work-in-progress limit. | F7: 3 | H7: 3 | J7: 3
A8: S-M0-04 | B8: M0 | C8: Communication | D8: Write clear status updates for stakeholders | E8: Writes Friday self-reports and stakeholder updates that lead with the answer and state impact, dates, risks and asks, and they go out without the Manager rewriting them. | F8: 2 | H8: 2 | J8: 3
A9: S-M0-05 | B9: M0 | C9: Documentation | D9: Capture knowledge as reviewed docs and Anki cards | E9: Turns sessions, shadowing and answered questions into OneNote pages, SOP lines and company-specific Anki cards with a Draft, Reviewed or Published status, and the cards pass the milestone spot check with zero factual errors. | F9: 2 | H9: 3 | J9: 3
A10: S-M0-06 | B10: M0 | C10: Communication | D10: Deliver a teach-back | E10: Explains a topic in 15 minutes using docs/templates/knowledge/teach-back.md, answers follow-up questions without notes, and says what they do not know instead of guessing. | F10: 2 | H10: 3 | J10: 3
A11: S-M0-07 | B11: M0 | C11: Business orientation | D11: Explain the business and its stakeholders | E11: Without notes, explains what we import, from where and into which countries, and keeps a 1-page stakeholder map showing what each group needs from the team and how tariff and cost news reaches them. | F11: 3 | H11: 3 | J11: 3
A12: S-M1-01 | B12: M1 | C12: Customs fundamentals | D12: Explain the life of a US import entry and who does what | E12: Without notes, walks through release, entry summary (CBP Form 7501), duty payment, liquidation and the protest window, and states what the importer of record, the licensed broker and CBP each own. | F12: 2 | H12: 3 | J12: 3
A13: S-M1-02 | B13: M1 | C13: Customs fundamentals | D13: Explain the Canada and Mexico import processes | E13: Explains the CBSA flow (release, CARM, Commercial Accounting Declaration, BN/RM account) and the Mexico flow (agente aduanal, pedimento, padrón de importadores, IVA), and names the data our team provides to each broker. | F13: 2 | H13: 2 | J13: 2
A14: S-M1-03 | B14: M1 | C14: Classification | D14: Classify an item using the GRIs | E14: Classifies a new item to 6-digit HS with written GRI reasoning backed by section and chapter notes, Explanatory Notes and CROSS rulings, finds the national line in the HTSUS, the Canada Customs Tariff and TIGIE, and flags doubtful cases for review. | F14: 2 | H14: 2 | J14: 2
A15: S-M1-04 | B15: M1 | C15: Customs fundamentals | D15: Calculate duties and fees for an entry line | E15: For an entry line, identifies the value basis, the rate column (general, USMCA or other preference, Chapter 99 additional duties) and fees such as MPF and HMF, and recomputes the duty to the cent or explains the difference. | F15: 2 | H15: 3 | J15: 3
A16: S-M1-05 | B16: M1 | C16: Origin & programs | D16: Apply USMCA rules of origin and certification | E16: Tests an item against its product-specific rule (tariff shift, RVC, de minimis) using its bill of materials, checks a certification for the nine minimum data elements, and states the importer's obligations if the claim fails. | F16: 1 | H16: 2 | J16: 2
... A79: S-M13-03 | B79: M13 | C79: SDLC | D79: Classify a change and plan its rollback | E79: Classifies each change as standard, normal or emergency, tells incidents, problems and changes apart, and writes a rollback plan with a verified backup, data clean-up steps and who is told, before any release. | F79: 0 | H79: 2 | J79: 3

Sheet Knowledge - Hire A
A1: Knowledge tracker: Hire A (Research track)
A2: Update Status, Date covered and Confidence as you go. Turn gaps into questions for your 1:1.
A4: Topic ID | B4: Module | C4: Priority | D4: Topic | E4: Learning objective | F4: Trainer | G4: Resource | H4: Target week | I4: Week starts | J4: Status | K4: Date covered | L4: Confidence (1-5) | M4: Card / doc written? | N4: Self-check question | O4: Notes
A5: K-M0-01 | B5: M0 | C5: Core | D5: Team, systems and processes the BSA team owns | E5: Explain what the BSA team owns (trade software, custom tools, trade data and analytics), its main internal customers, and where Research and Standard Cost fit. | F5: Manager | G5: [COMPANY: team charter and org chart] | H5: 1 | I5: =ProgramStart+(H5-1)*7 | J5: Not started | N5: Which three processes or systems would stop first if the BSA team were out for a week, and who would notice?
A6: K-M0-02 | B6: M0 | C6: Core | D6: The 30/60/90 plan, weekly rhythm and milestone evidence | E6: Name your day-30 Must criteria and their evidence, and run the weekly cadence (1:1, Friday self-report, question log, teach-back) without reminders. | F6: Manager | G6: docs/03-check-ins-and-scorecards.md | H6: 1 | I6: =ProgramStart+(H6-1)*7 | J6: Not started | N6: What evidence is due two working days before your day-30 review, and when is your Friday self-report due?
A7: K-M0-03 | B7: M0 | C7: Core | D7: Planning a 40-hour week with 5-8 guided hours | E7: Build a weekly plan where every self-study block has a defined output (cards, a question-log entry or a doc section). | F7: Self-study | G7: docs/05-time-management.md | H7: 1 | I7: =ProgramStart+(H7-1)*7 | J7: Not started | N7: What is the output of each self-study block on your calendar this week?
A8: K-M0-04 | B8: M0 | C8: Core | D8: Jira and Planner: how the team tracks work | E8: Create and maintain Jira items to the team standard on [COMPANY: Jira project and board], and keep Planner tasks in sync where the team uses them. | F8: Manager | G8: docs/templates/bsa/07-jira-epic-story.md | H8: 1 | I8: =ProgramStart+(H8-1)*7 | J8: Not started | N8: What must a Jira item contain before you start work on it, and how often do you update its status?
A9: K-M0-05 | B9: M0 | C9: Core | D9: OneNote structure, document status and Anki card writing | E9: File notes in the right OneNote section with a Draft, Reviewed or Published status, and write atomic, sourced company-specific Anki cards. | F9: Self-study | G9: docs/templates/knowledge/anki-card-writing-guide.md | H9: 1 | I9: =ProgramStart+(H9-1)*7 | J9: Not started | N9: Which document statuses may go into the shared OneNote sections, and what makes a good company-specific card?
A10: K-M0-06 | B10: M0 | C10: Core | D10: Business overview: products, suppliers, source countries, customers | E10: Explain what the company imports, from where, into which countries and through which channels. Hire B: refresher only; skim it for 30 minutes on Tue 10/20 (no quiz) and move the saved time to Oracle cost data. | F10: Self-study | G10: [COMPANY: business overview materials] | H10: 1 | I10: =ProgramStart+(H10-1)*7 | J10: Not started | N10: Which product families and source countries account for most of our import value?
A11: K-M0-07 | B11: M0 | C11: Core | D11: Boundary rule and maker-checker control | E11: State who owns the WHAT and who owns the $ for a tariff action, and what a documented checker sign-off must contain. | F11: Manager | G11: docs/01-30-60-90-plan.md | H11: 1 | I11: =ProgramStart+(H11-1)*7 | J11: Not started | N11: For a new tariff action, who owns the effective date, who owns the margin impact, and what must happen before either is released?
A12: K-M0-08 | B12: M0 | C12: Core | D12: Stakeholder map and intro meetings | E12: Meet each stakeholder group (30-minute intro meetings in W3-W4, booked by the Manager) and record who they are, what they need from the team and how tariff and cost news reaches them today. | F12: Shadow | G12: [COMPANY: stakeholder list] | H12: 4 | I12: =ProgramStart+(H12-1)*7 | J12: Not started | N12: Who in the business hears about a new tariff action first today, and who needs its cost impact?
A13: K-M1-01 | B13: M1 | C13: Core | D13: US import roles: importer of record, licensed broker, CBP; reasonable care | E13: Explain who is legally responsible for what on a US entry and what reasonable care requires of us as importer. | F13: Senior | G13: docs/primers/customs-trade-compliance-primer.md | H13: 1 | I13: =ProgramStart+(H13-1)*7 | J13: Not started | N13: If the broker files a wrong HTS code using data we supplied, who is liable to CBP and why?
A14: K-M1-02 | B14: M1 | C14: Core | D14: Life of a US entry: release, entry summary, duty payment, liquidation, protest | E14: Describe each stage of a US formal entry, the documents involved and the statutory windows that matter for corrections. | F14: Senior | G14: https://www.cbp.gov/document/publications/importing-united-states | H14: 1 | I14: =ProgramStart+(H14-1)*7 | J14: Not started | N14: What is the difference between cargo release (CBP Form 3461) and the entry summary (CBP Form 7501), and what event starts the protest clock?
A15: K-M1-03 | B15: M1 | C15: Core | D15: US duties and fees: ad valorem and specific duty, MPF, HMF, AD/CVD awareness | E15: Compute duty and fees for a sample entry line and explain when each fee applies. | F15: Senior | G15: docs/primers/customs-trade-compliance-primer.md | H15: 1 | I15: =ProgramStart+(H15-1)*7 | J15: Not started | N15: Why does an ocean entry usually carry HMF while a truck entry from Mexico does not?
A16: K-M1-04 | B16: M1 | C16: Core | D16: ACE, ABI, ISF and PGA filings around a US entry | E16: Explain what ACE, ABI, ISF and PGA filings each do, and which ACE reports the team can use to audit broker filings. | F16: Self-study | G16: https://www.cbp.gov/trade/automated | H16: 2 | I16: =ProgramStart+(H16-1)*7 | J16: Not started | N16: For which transport mode is an ISF required, and when must it be filed?
... A143: K-M13-07 | B143: M13 | C143: Core | D143: Before the e2open kickoff: the vendor method and test phases | E143: Explain how a vendor GTM implementation moves from design to cutover, and what SIT and UAT each prove. | F143: Self-study | G143: docs/primers/sdlc-primer.md | H143: 12 | I143: =ProgramStart+(H143-1)*7 | J143: Not started | N143: In a vendor implementation, what is the difference between SIT and UAT, and what is decided at cutover?

Sheet Knowledge - Hire B
A1: Knowledge tracker: Hire B (Standard Cost track)
A2: Update Status, Date covered and Confidence as you go. Turn gaps into questions for your 1:1.
A4: Topic ID | B4: Module | C4: Priority | D4: Topic | E4: Learning objective | F4: Trainer | G4: Resource | H4: Target week | I4: Week starts | J4: Status | K4: Date covered | L4: Confidence (1-5) | M4: Card / doc written? | N4: Self-check question | O4: Notes
A5: K-M0-01 | B5: M0 | C5: Core | D5: Team, systems and processes the BSA team owns | E5: Explain what the BSA team owns (trade software, custom tools, trade data and analytics), its main internal customers, and where Research and Standard Cost fit. | F5: Manager | G5: [COMPANY: team charter and org chart] | H5: 1 | I5: =ProgramStart+(H5-1)*7 | J5: Not started | N5: Which three processes or systems would stop first if the BSA team were out for a week, and who would notice?
A6: K-M0-02 | B6: M0 | C6: Core | D6: The 30/60/90 plan, weekly rhythm and milestone evidence | E6: Name your day-30 Must criteria and their evidence, and run the weekly cadence (1:1, Friday self-report, question log, teach-back) without reminders. | F6: Manager | G6: docs/03-check-ins-and-scorecards.md | H6: 1 | I6: =ProgramStart+(H6-1)*7 | J6: Not started | N6: What evidence is due two working days before your day-30 review, and when is your Friday self-report due?
A7: K-M0-03 | B7: M0 | C7: Core | D7: Planning a 40-hour week with 5-8 guided hours | E7: Build a weekly plan where every self-study block has a defined output (cards, a question-log entry or a doc section). | F7: Self-study | G7: docs/05-time-management.md | H7: 1 | I7: =ProgramStart+(H7-1)*7 | J7: Not started | N7: What is the output of each self-study block on your calendar this week?
A8: K-M0-04 | B8: M0 | C8: Core | D8: Jira and Planner: how the team tracks work | E8: Create and maintain Jira items to the team standard on [COMPANY: Jira project and board], and keep Planner tasks in sync where the team uses them. | F8: Manager | G8: docs/templates/bsa/07-jira-epic-story.md | H8: 1 | I8: =ProgramStart+(H8-1)*7 | J8: Not started | N8: What must a Jira item contain before you start work on it, and how often do you update its status?
A9: K-M0-05 | B9: M0 | C9: Core | D9: OneNote structure, document status and Anki card writing | E9: File notes in the right OneNote section with a Draft, Reviewed or Published status, and write atomic, sourced company-specific Anki cards. | F9: Self-study | G9: docs/templates/knowledge/anki-card-writing-guide.md | H9: 1 | I9: =ProgramStart+(H9-1)*7 | J9: Not started | N9: Which document statuses may go into the shared OneNote sections, and what makes a good company-specific card?
A10: K-M0-06 | B10: M0 | C10: Core | D10: Business overview: products, suppliers, source countries, customers | E10: Explain what the company imports, from where, into which countries and through which channels. Hire B: refresher only; skim it for 30 minutes on Tue 10/20 (no quiz) and move the saved time to Oracle cost data. | F10: Self-study | G10: [COMPANY: business overview materials] | H10: 1 | I10: =ProgramStart+(H10-1)*7 | J10: Not started | N10: Which product families and source countries account for most of our import value?
A11: K-M0-07 | B11: M0 | C11: Core | D11: Boundary rule and maker-checker control | E11: State who owns the WHAT and who owns the $ for a tariff action, and what a documented checker sign-off must contain. | F11: Manager | G11: docs/01-30-60-90-plan.md | H11: 1 | I11: =ProgramStart+(H11-1)*7 | J11: Not started | N11: For a new tariff action, who owns the effective date, who owns the margin impact, and what must happen before either is released?
A12: K-M0-08 | B12: M0 | C12: Core | D12: Stakeholder map and intro meetings | E12: Meet each stakeholder group (30-minute intro meetings in W3-W4, booked by the Manager) and record who they are, what they need from the team and how tariff and cost news reaches them today. | F12: Shadow | G12: [COMPANY: stakeholder list] | H12: 4 | I12: =ProgramStart+(H12-1)*7 | J12: Not started | N12: Who in the business hears about a new tariff action first today, and who needs its cost impact?
A13: K-M1-01 | B13: M1 | C13: Core | D13: US import roles: importer of record, licensed broker, CBP; reasonable care | E13: Explain who is legally responsible for what on a US entry and what reasonable care requires of us as importer. | F13: Senior | G13: docs/primers/customs-trade-compliance-primer.md | H13: 1 | I13: =ProgramStart+(H13-1)*7 | J13: Not started | N13: If the broker files a wrong HTS code using data we supplied, who is liable to CBP and why?
A14: K-M1-02 | B14: M1 | C14: Core | D14: Life of a US entry: release, entry summary, duty payment, liquidation, protest | E14: Describe each stage of a US formal entry, the documents involved and the statutory windows that matter for corrections. | F14: Senior | G14: https://www.cbp.gov/document/publications/importing-united-states | H14: 1 | I14: =ProgramStart+(H14-1)*7 | J14: Not started | N14: What is the difference between cargo release (CBP Form 3461) and the entry summary (CBP Form 7501), and what event starts the protest clock?
A15: K-M1-03 | B15: M1 | C15: Core | D15: US duties and fees: ad valorem and specific duty, MPF, HMF, AD/CVD awareness | E15: Compute duty and fees for a sample entry line and explain when each fee applies. | F15: Senior | G15: docs/primers/customs-trade-compliance-primer.md | H15: 1 | I15: =ProgramStart+(H15-1)*7 | J15: Not started | N15: Why does an ocean entry usually carry HMF while a truck entry from Mexico does not?
A16: K-M1-04 | B16: M1 | C16: Core | D16: ACE, ABI, ISF and PGA filings around a US entry | E16: Explain what ACE, ABI, ISF and PGA filings each do, and which ACE reports the team can use to audit broker filings. | F16: Self-study | G16: https://www.cbp.gov/trade/automated | H16: 2 | I16: =ProgramStart+(H16-1)*7 | J16: Not started | N16: For which transport mode is an ISF required, and when must it be filed?
... A143: K-M13-07 | B143: M13 | C143: Core | D143: Before the e2open kickoff: the vendor method and test phases | E143: Explain how a vendor GTM implementation moves from design to cutover, and what SIT and UAT each prove. | F143: Self-study | G143: docs/primers/sdlc-primer.md | H143: 12 | I143: =ProgramStart+(H143-1)*7 | J143: Not started | N143: In a vendor implementation, what is the difference between SIT and UAT, and what is decided at cutover?

Sheet Tool Inventory
A1: Custom tool inventory
A2: Built by the hires in week 2. One row per tool; one tool doc per row (docs/templates/knowledge/tool-doc.md).
A4: Tool ID | B4: Tool name | C4: Purpose / process supported | D4: Business users | E4: Stack | F4: Where code / file lives | G4: Data sources | H4: Run frequency | I4: Knowledge holder today | J4: Backup | K4: Documentation | L4: Known issues | M4: Risk if it breaks | N4: e2open impact | O4: Assigned learner | P4: Tool doc link | Q4: Target doc date
A5: T-01 | B5: [COMPANY: tool 1]
A6: T-02 | B6: [COMPANY: tool 2]
A7: T-03 | B7: [COMPANY: tool 3]
A8: T-04 | B8: [COMPANY: tool 4]
A9: T-05 | B9: [COMPANY: tool 5]
A10: T-06 | B10: [COMPANY: tool 6]
A11: T-07 | B11: [COMPANY: tool 7]
A12: T-08 | B12: [COMPANY: tool 8]
A13: T-09 | B13: [COMPANY: tool 9]
A14: T-10 | B14: [COMPANY: tool 10]
A15: T-11 | B15: [COMPANY: tool 11]
A16: T-12 | B16: [COMPANY: tool 12]
... A19: T-15 | B19: [COMPANY: tool 15]

Sheet Glossary
A1: Glossary
A2: Filter by country or category. Add company-specific terms on the company copy only.
A4: Term | B4: Definition | C4: Country | D4: Category
A5: ABI (Automated Broker Interface) | B5: The electronic interface brokers and self-filers use to transmit entry and entry summary data to ACE. | C5: US | D5: Customs
A6: Acceptance criteria | B6: Specific, testable conditions a deliverable must meet to be accepted, agreed before work starts and often written as Given/When/Then. | C6: All | D6: BSA
A7: Accumulation (USMCA) | B7: Rule that lets production and originating materials from any of the three USMCA countries count toward a good's origin. | C7: All | D7: Origin
A8: ACE (Automated Commercial Environment) | B8: CBP's single-window system for import and export processing. Brokers file entries in it; the ACE Portal gives importers reports on their own entries. | C8: US | D8: Customs
A9: Ad valorem, specific and compound duty | B9: Ad valorem duty is a percentage of customs value, specific duty a fixed amount per unit such as per kg, and compound duty combines both. | C9: All | D9: Customs
A10: AD/CVD (antidumping and countervailing duties) | B10: Additional duties that offset dumping or subsidies on specific goods from specific countries, often by manufacturer. US cases run through Commerce and USITC; Canadian ones through CBSA and CITT. | C10: All | D10: Customs
A11: AES and ACE AESDirect | B11: The Automated Export System is the export part of ACE where EEI is filed; ACE AESDirect is the Census Bureau's free web portal for filing it. | C11: US | D11: Exports
A12: Agente aduanal | B12: Mexican customs broker holding a patente from the customs authority; files pedimentos for the importer. The importer remains liable, and the agente shares liability for the taxes. | C12: MX | D12: Customs
A13: AMPS (Administrative Monetary Penalty System) | B13: Canada's civil penalty regime for customs contraventions. Penalty amounts are set by contravention in CBSA's Master Penalty Document, rise for repeat contraventions, and are issued against the importer's BN15. | C13: CA | D13: Customs
A14: ANAM (Agencia Nacional de Aduanas de México) | B14: Mexico's customs agency since 2022, responsible for customs offices, inspections and customs operations. | C14: MX | D14: Customs
A15: Anexo 24 | B15: RGCE annex setting the automated inventory control system IMMEX companies must keep for temporary imports, tracking each input from entry to export or change of regime. | C15: MX | D15: Programs
... A218: z-score | B218: Standard deviations from the mean: z = (value - mean) / sample standard deviation. Exercise 11 flags |z| > 3. Like any outlier rule, it marks values to investigate, not to delete. | C218: All | D218: Data
